Metadata-Version: 2.1
Name: pyFLAC
Version: 3.0.0
Summary: A Python wrapper for libFLAC
Author-email: Joe Todd <joe.todd@sonos.com>
License: Apache-2.0
Keywords: lossless,compression,flac,bindings,audio
Classifier: Development Status :: 5 - Production/Stable
Classifier: Intended Audience :: Developers
Classifier: Intended Audience :: Science/Research
Classifier: License :: OSI Approved :: Apache Software License
Classifier: Operating System :: OS Independent
Classifier: Programming Language :: Python :: 3.8
Classifier: Programming Language :: Python :: 3.9
Classifier: Programming Language :: Python :: 3.10
Classifier: Programming Language :: Python :: 3.11
Classifier: Programming Language :: Python :: 3.12
Classifier: Topic :: Multimedia :: Sound/Audio
Requires-Python: >=3.8
License-File: LICENSE.txt
Requires-Dist: cffi>=1.4.0
Requires-Dist: numpy>=1.22
Requires-Dist: SoundFile>=0.11
